widget_jsmol/__init__.py
widget_jsmol/_frontend.py
widget_jsmol/_version.py
widget_jsmol/jsmol.py
widget_jsmol/labextension/widget_jsmol-2.0.0.tgz
widget_jsmol/nbextension/__init__.py
widget_jsmol/nbextension/static/extension.js
widget_jsmol/nbextension/static/index.js
widget_jsmol/nbextension/static/index.js.map
widget_jsmol/tests/__init__.py
widget_jsmol/tests/conftest.py
widget_jsmol/tests/test_example.py
widget_jsmol/tests/test_nbextension_path.py
widget_jsmol-2.0.0.data/data/etc/jupyter/nbconfig/notebook.d/widget_jsmol.json
widget_jsmol-2.0.0.data/data/share/jupyter/lab/extensions/widget_jsmol-2.0.0.tgz
widget_jsmol-2.0.0.data/data/share/jupyter/nbextensions/widget_jsmol/extension.js
widget_jsmol-2.0.0.data/data/share/jupyter/nbextensions/widget_jsmol/index.js
widget_jsmol-2.0.0.data/data/share/jupyter/nbextensions/widget_jsmol/index.js.map
widget_jsmol-2.0.0.dist-info/LICENSE.txt
widget_jsmol-2.0.0.dist-info/METADATA
widget_jsmol-2.0.0.dist-info/WHEEL
widget_jsmol-2.0.0.dist-info/top_level.txt
widget_jsmol-2.0.0.dist-info/RECORD
