Metadata-Version: 2.1
Name: widget-jsmol
Version: 2.0.0
Summary: A Jupyter widget to use Jmol/Jsmol.
Home-page: https://github.com/osscar-org/widget-jsmol
Author: Dou Du
Author-email: dou.du@epfl.ch
License: BSD
Keywords: Jupyter,Widgets,IPython
Platform: Linux
Platform: Mac OS X
Platform: Windows
Classifier: Intended Audience :: Developers
Classifier: Intended Audience :: Science/Research
Classifier: License :: OSI Approved :: BSD License
Classifier: Programming Language :: Python
Classifier: Programming Language :: Python :: 3
Classifier: Programming Language :: Python :: 3.4
Classifier: Programming Language :: Python :: 3.5
Classifier: Programming Language :: Python :: 3.6
Classifier: Programming Language :: Python :: 3.7
Classifier: Framework :: Jupyter
Requires-Dist: ipywidgets (>=7.0.0)
Provides-Extra: docs
Requires-Dist: sphinx (>=1.5) ; extra == 'docs'
Requires-Dist: recommonmark ; extra == 'docs'
Requires-Dist: sphinx-rtd-theme ; extra == 'docs'
Requires-Dist: nbsphinx (<0.4.0,>=0.2.13) ; extra == 'docs'
Requires-Dist: jupyter-sphinx ; extra == 'docs'
Requires-Dist: nbsphinx-link ; extra == 'docs'
Requires-Dist: pytest-check-links ; extra == 'docs'
Requires-Dist: pypandoc ; extra == 'docs'
Provides-Extra: examples
Provides-Extra: test
Requires-Dist: pytest (>=3.6) ; extra == 'test'
Requires-Dist: pytest-cov ; extra == 'test'
Requires-Dist: nbval ; extra == 'test'
